{
  "profile_name": "Sci-Fi",
  "description": "Correction dictionary for science fiction franchises including Dune, Star Wars, Star Trek, The Expanse, Foundation, and more.",
  "author": "Samsara",
  "version": "1.0",
  "created": "2026-02-14",
  "vocabulary": [
    "Arrakis", "Atreides", "Harkonnen", "Fremen", "Muad'Dib", "Kwisatz Haderach",
    "Bene Gesserit", "Bene Tleilax", "Sardaukar", "Stilgar", "Chani", "Leto",
    "Paul Atreides", "Baron Harkonnen", "Feyd-Rautha", "Duncan Idaho", "Thufir Hawat",
    "Gurney Halleck", "Liet-Kynes", "Shadout Mapes", "Stilltent", "Stillsuit",
    "Ornithopter", "Sandworm", "Shai-Hulud", "Melange", "Spice", "Sietch",
    "Caladan", "Giedi Prime", "Salusa Secundus", "Kaitain", "Ix", "Tleilax",
    "Landsraad", "CHOAM", "Mentat", "Gom Jabbar", "Crysknife", "Thumper",
    "Spacing Guild", "Heighliner", "Lisan al Gaib", "Reverend Mother",
    "Coruscant", "Tatooine", "Naboo", "Kashyyyk", "Dagobah", "Hoth",
    "Endor", "Mustafar", "Kamino", "Geonosis", "Mandalore", "Bespin",
    "Alderaan", "Jakku", "Exegol", "Ahch-To",
    "Palpatine", "Anakin", "Skywalker", "Obi-Wan", "Kenobi", "Yoda",
    "Chewbacca", "Leia", "Organa", "Padmé", "Amidala", "Mace Windu",
    "Qui-Gon", "Dooku", "Grievous", "Ahsoka", "Tano", "Thrawn",
    "Mandalorian", "Grogu", "Din Djarin", "Bo-Katan", "Darksaber",
    "Lightsaber", "Kyber", "Holocron", "Beskar", "Carbonite",
    "Midi-chlorian", "Padawan", "Youngling", "Sith", "Jedi",
    "TIE Fighter", "X-Wing", "Millennium Falcon", "Star Destroyer",
    "Death Star", "AT-AT", "AT-ST", "Wookiee", "Twi'lek", "Zabrak",
    "Togruta", "Rodian", "Hutt", "Jawas", "Tusken",
    "Starfleet", "Vulcan", "Klingon", "Romulan", "Ferengi", "Cardassian",
    "Bajoran", "Borg", "Trill", "Betazoid", "Andorian", "Tellarite",
    "Picard", "Riker", "Worf", "Data", "Geordi", "La Forge",
    "Janeway", "Chakotay", "Tuvok", "Seven of Nine", "B'Elanna",
    "Sisko", "Dax", "Odo", "Quark", "Spock", "McCoy", "Uhura",
    "Scotty", "Kirk", "Enterprise", "Defiant", "Voyager",
    "Holodeck", "Tricorder", "Phaser", "Photon Torpedo", "Warp Drive",
    "Dilithium", "Transporter", "Replicator", "Turbolift",
    "Qeng Ho", "Holtzman", "Butlerian Jihad",
    "Ender Wiggin", "Bugger", "Formic", "Battle School", "Ender's Game",
    "Valentine", "Peter Wiggin", "Hive Queen", "Ansible",
    "Rocinante", "Holden", "Naomi Nagata", "Amos Burton", "Alex Kamal",
    "Bobbie Draper", "Chrisjen Avasarala", "Protomolecule", "Epstein Drive",
    "Belter", "Tycho", "Ceres", "Eros", "Ganymede", "Medina Station",
    "Laconia", "Ring Gate", "Donnager", "Canterbury",
    "Hari Seldon", "Foundation", "Trantor", "Terminus", "Psychohistory",
    "Mule", "Second Foundation", "Gaia", "Encyclopedists",
    "Zaphod Beeblebrox", "Ford Prefect", "Trillian", "Marvin",
    "Magrathea", "Vogon", "Babel Fish", "Hitchhiker",
    "Neuromancer", "Wintermute", "Tessier-Ashpool", "Sprawl",
    "Cyberspace", "ICE", "Cyberdeck", "Netrunner", "Megacorp",
    "Hyperion", "Shrike", "Hegemony", "Ousters", "TechnoCore",
    "Farcaster", "Hawking Drive", "Kassad", "Endymion",
    "Trisolaran", "Sophon", "Dark Forest", "Wallfacer", "Swordholder",
    "Deterrence", "Droplet", "Luo Ji", "Cheng Xin", "Ye Wenjie",
    "Shepard", "Garrus", "Tali", "Liara", "Wrex", "Mordin",
    "Normandy", "Citadel", "Spectre", "Reaper", "Prothean",
    "Turian", "Asari", "Krogan", "Quarian", "Geth", "Cerberus",
    "Mass Relay", "Element Zero", "Eezo", "Omni-tool", "Biotic",
    "Replicant", "Nexus-6", "Tyrell", "Deckard", "Roy Batty",
    "Rachael", "Voight-Kampff",
    "HAL 9000", "Monolith", "Discovery One",
    "Xenomorph", "Nostromo", "Weyland-Yutani", "Facehugger",
    "Chestburster", "LV-426", "Ripley", "Sulaco", "Prometheus"
  ],
  "corrections": {
    "a tray dis": "Atreides",
    "a tray deez": "Atreides",
    "at tray deez": "Atreides",
    "harken in": "Harkonnen",
    "har conan": "Harkonnen",
    "kwisatz hatter rack": "Kwisatz Haderach",
    "quiz ats had a rack": "Kwisatz Haderach",
    "benny jess or it": "Bene Gesserit",
    "benny jessica": "Bene Gesserit",
    "ben eh jess or it": "Bene Gesserit",
    "maud dib": "Muad'Dib",
    "mood dib": "Muad'Dib",
    "sardaukar": "Sardaukar",
    "sardine car": "Sardaukar",
    "sard oh car": "Sardaukar",
    "a rack is": "Arrakis",
    "Iraq is": "Arrakis",
    "shai hulud": "Shai-Hulud",
    "shy who lud": "Shai-Hulud",
    "ornithopter": "Ornithopter",
    "still suit": "Stillsuit",
    "gom jab bar": "Gom Jabbar",
    "crys knife": "Crysknife",
    "high liner": "Heighliner",
    "lisa al gabe": "Lisan al Gaib",
    "corr you scant": "Coruscant",
    "corus cant": "Coruscant",
    "tat to ween": "Tatooine",
    "tat ooh ween": "Tatooine",
    "cash eek": "Kashyyyk",
    "cash ick": "Kashyyyk",
    "nah boo": "Naboo",
    "all duran": "Alderaan",
    "alder on": "Alderaan",
    "palatine": "Palpatine",
    "palpa teen": "Palpatine",
    "anakin": "Anakin",
    "obi wan": "Obi-Wan",
    "obi one": "Obi-Wan",
    "can obi": "Kenobi",
    "chew baka": "Chewbacca",
    "chew bacca": "Chewbacca",
    "pod may": "Padmé",
    "padmay": "Padmé",
    "ahh so ka": "Ahsoka",
    "a soaker": "Ahsoka",
    "man delorian": "Mandalorian",
    "grow goo": "Grogu",
    "gro goo": "Grogu",
    "dark saber": "Darksaber",
    "light saber": "Lightsaber",
    "kyber": "Kyber",
    "bass car": "Beskar",
    "midi chlorian": "Midi-chlorian",
    "middie chlorine": "Midi-chlorian",
    "twilek": "Twi'lek",
    "twi lek": "Twi'lek",
    "vulcan": "Vulcan",
    "cling on": "Klingon",
    "klingon": "Klingon",
    "rom you lan": "Romulan",
    "for engi": "Ferengi",
    "cardassian": "Cardassian",
    "by jour an": "Bajoran",
    "picard": "Picard",
    "janeway": "Janeway",
    "chaco tay": "Chakotay",
    "to vok": "Tuvok",
    "below anna": "B'Elanna",
    "hollow deck": "Holodeck",
    "try quarter": "Tricorder",
    "die lithium": "Dilithium",
    "roche nante": "Rocinante",
    "rossy nante": "Rocinante",
    "proto molecule": "Protomolecule",
    "epstein drive": "Epstein Drive",
    "ave a sarala": "Avasarala",
    "harry seldon": "Hari Seldon",
    "psycho history": "Psychohistory",
    "trans store": "Trantor",
    "zaphod beeble brox": "Zaphod Beeblebrox",
    "ford prefect": "Ford Prefect",
    "vogon": "Vogon",
    "babble fish": "Babel Fish",
    "neuro mancer": "Neuromancer",
    "winter mute": "Wintermute",
    "try solar an": "Trisolaran",
    "tree solar": "Trisolaran",
    "sofa on": "Sophon",
    "wall facer": "Wallfacer",
    "low G": "Luo Ji",
    "chung shin": "Cheng Xin",
    "yay when jay": "Ye Wenjie",
    "garrus": "Garrus",
    "tally": "Tali",
    "leah raw": "Liara",
    "more din": "Mordin",
    "to rian": "Turian",
    "a sorry": "Asari",
    "crow gan": "Krogan",
    "quarry an": "Quarian",
    "gate": "Geth",
    "replicant": "Replicant",
    "xenomorph": "Xenomorph",
    "zeno morph": "Xenomorph",
    "nostromo": "Nostromo",
    "wayland you tawny": "Weyland-Yutani",
    "weyland utani": "Weyland-Yutani",
    "face hugger": "Facehugger"
  },
  "initial_prompt": ""
}
